my_app_core-0.1.0.dist-info/licenses/LICENSE
myapp/__init__.py
myapp/core.py
myapp/plugin_base.py
myapp/plugin_manager.py
my_app_core-0.1.0.dist-info/METADATA
my_app_core-0.1.0.dist-info/WHEEL
my_app_core-0.1.0.dist-info/entry_points.txt
my_app_core-0.1.0.dist-info/top_level.txt
my_app_core-0.1.0.dist-info/RECORD
