Metadata-Version: 2.4
Name: my-app-core
Version: 0.1.0
Summary: 支持插件的Python应用
License-File: LICENSE
Dynamic: license-file
